python_utility_functions/__init__.py
python_utility_functions/image_utilities.py
python_utility_functions/io_utilities.py
python_utility_functions/path_utilities.py
python_utility_functions/python_utilities.py
python_utility_functions/visualization_utilities.py
python_utility_functions-1.0.7.dist-info/LICENSE
python_utility_functions-1.0.7.dist-info/METADATA
python_utility_functions-1.0.7.dist-info/WHEEL
python_utility_functions-1.0.7.dist-info/top_level.txt
python_utility_functions-1.0.7.dist-info/RECORD
