Metadata-Version: 2.1
Name: python-utility-functions
Version: 1.0.7
Summary: Utility funtions in python
Home-page: https://github.com/daniel-men/python_utility_functions
Author: Daniel Mensing
Author-email: daniel.mensing@gmx.net
License: UNKNOWN
Platform: UNKNOWN
License-File: LICENSE
Requires-Dist: opencv-python
Requires-Dist: pillow
Requires-Dist: pydicom
Requires-Dist: numpy
Requires-Dist: matplotlib
Requires-Dist: lmdbm
